{
  "_format": "hh-sol-cache-2",
  "files": {
    "/mnt/e/hardhat-smart-contracts/contracts/EnergyMarketplace.sol": {
      "lastModificationDate": 1726074670629,
      "contentHash": "1c08a870c74d11c1c4cce6c49fdb5fb6",
      "sourceName": "contracts/EnergyMarketplace.sol",
      "solcConfig": {
        "version": "0.8.24",
        "settings": {
          "evmVersion": "paris",
          "optimizer": {
            "enabled": false,
            "runs": 200
          },
          "outputSelection": {
            "*": {
              "*": [
                "abi",
                "evm.bytecode",
                "evm.deployedBytecode",
                "evm.methodIdentifiers",
                "metadata"
              ],
              "": [
                "ast"
              ]
            }
          }
        }
      },
      "imports": [],
      "versionPragmas": [
        "^0.8.24"
      ],
      "artifacts": [
        "EnergyMarketplace"
      ]
    },
    "/mnt/e/hardhat-smart-contracts/contracts/Lock.sol": {
      "lastModificationDate": 1726069485648,
      "contentHash": "dacf0d5cb5b45dc83086de5bc1c26c2c",
      "sourceName": "contracts/Lock.sol",
      "solcConfig": {
        "version": "0.8.24",
        "settings": {
          "evmVersion": "paris",
          "optimizer": {
            "enabled": false,
            "runs": 200
          },
          "outputSelection": {
            "*": {
              "*": [
                "abi",
                "evm.bytecode",
                "evm.deployedBytecode",
                "evm.methodIdentifiers",
                "metadata"
              ],
              "": [
                "ast"
              ]
            }
          }
        }
      },
      "imports": [],
      "versionPragmas": [
        "^0.8.24"
      ],
      "artifacts": [
        "Lock"
      ]
    },
    "/mnt/e/hardhat-smart-contracts/contracts/MyContract.sol": {
      "lastModificationDate": 1726069485655,
      "contentHash": "0d953c8406547d089e50482ad84dec7b",
      "sourceName": "contracts/MyContract.sol",
      "solcConfig": {
        "version": "0.8.24",
        "settings": {
          "evmVersion": "paris",
          "optimizer": {
            "enabled": false,
            "runs": 200
          },
          "outputSelection": {
            "*": {
              "*": [
                "abi",
                "evm.bytecode",
                "evm.deployedBytecode",
                "evm.methodIdentifiers",
                "metadata"
              ],
              "": [
                "ast"
              ]
            }
          }
        }
      },
      "imports": [],
      "versionPragmas": [
        "^0.8.24"
      ],
      "artifacts": [
        "MyContract"
      ]
    }
  }
}
